checked/__init__.py
checked/cli.py
checked/gui.py
checked/translations.json
checked-0.1.2.dist-info/METADATA
checked-0.1.2.dist-info/WHEEL
checked-0.1.2.dist-info/entry_points.txt
checked-0.1.2.dist-info/RECORD
