Metadata-Version: 2.3
Name: checked
Version: 0.1.2
Summary: A simple app to convert HTML files to Spreadsheets, for Fact-Checking
Author: António Assunção
Author-email: larus-argentatus@riseup.net
Requires-Python: >=3.13, <3.14
Classifier: Programming Language :: Python :: 3
Classifier: Programming Language :: Python :: 3.13
Requires-Dist: beautifulsoup4 (==4.12.3)
Requires-Dist: odfpy (==1.4.1)
Requires-Dist: pandas (==2.2.3)
